Workbook

Sheet ramo
A1: Calculadora universal de precios para crochet
A3: Datos del producto
A4: Nombre / referencia | B4: ramo
A5: Tiempo total (horas) | B5: 2
A6: Mano de obra por hora | B6: =Config!B4 -> 1500
A7: Costo mano de obra | B7: =B5*B6 -> 3000
A9: Materiales y accesorios
A10: Material / accesorio | B10: Precio compra | C10: Cantidad comprada | D10: Cantidad usada | E10: Unidad | F10: Costo usado | G10: Notas | H10: Tipo
A11: Lana / hilo principal | B11: 2600 | C11: 100 | D11: 25 | E11: g | F11: =IFERROR((B11/C11)*D11,0) -> 650 | G11: Ej.: ovillo de 100 g | H11: Material
A12: Lana / hilo secundario | B12: 0 | C12: 0 | D12: 0 | E12: g | F12: =IFERROR((B12/C12)*D12,0) -> 0 | H12: Material
A13: Zíper | B13: 0 | C13: 1 | D13: 0 | E13: unidad | F13: =IFERROR((B13/C13)*D13,0) -> 0 | H13: Accesorio
A14: Llavín / herraje | B14: 50 | C14: 1 | D14: 0 | E14: unidad | F14: =IFERROR((B14/C14)*D14,0) -> 0 | H14: Accesorio
A15: broches | B15: 625 | C15: 30 | D15: 0 | E15: unidad | F15: =IFERROR((B15/C15)*D15,0) -> 0 | H15: Material
A16: ojitos | B16: 250 | C16: 5 | D16: 0 | F16: =IFERROR((B16/C16)*D16,0) -> 0 | H16: Material
A17: relleno | B17: 5400 | C17: 1000 | D17: 0 | E17: g | F17: =IFERROR((B17/C17)*D17,0) -> 0 | H17: Material
B18: 0 | C18: 1 | D18: 0 | F18: =IFERROR((B18/C18)*D18,0) -> 0 | H18: Material
B19: 0 | C19: 1 | D19: 0 | F19: =IFERROR((B19/C19)*D19,0) -> 0 | H19: Material
B20: 0 | C20: 1 | D20: 0 | F20: =IFERROR((B20/C20)*D20,0) -> 0 | H20: Material
B21: 0 | C21: 1 | D21: 0 | F21: =IFERROR((B21/C21)*D21,0) -> 0 | H21: Material
B22: 0 | C22: 1 | D22: 0 | F22: =IFERROR((B22/C22)*D22,0) -> 0 | H22: Material
B23: 0 | C23: 1 | D23: 0 | F23: =IFERROR((B23/C23)*D23,0) -> 0 | H23: Material
B24: 0 | C24: 1 | D24: 0 | F24: =IFERROR((B24/C24)*D24,0) -> 0 | H24: Material
B25: 0 | C25: 1 | D25: 0 | F25: =IFERROR((B25/C25)*D25,0) -> 0 | H25: Material
B26: 0 | C26: 1 | D26: 0 | F26: =IFERROR((B26/C26)*D26,0) -> 0 | H26: Material
B27: 0 | C27: 1 | D27: 0 | F27: =IFERROR((B27/C27)*D27,0) -> 0 | H27: Material
B28: 0 | C28: 1 | D28: 0 | F28: =IFERROR((B28/C28)*D28,0) -> 0 | H28: Material
B29: 0 | C29: 1 | D29: 0 | F29: =IFERROR((B29/C29)*D29,0) -> 0 | H29: Material
B30: 0 | C30: 1 | D30: 0 | F30: =IFERROR((B30/C30)*D30,0) -> 0 | H30: Material
A32: Resumen de precio
A33: Costo materiales/accesorios | B33: =SUM(F11:F30) -> 650 | D33: Indicadores
A34: Costo mano de obra | B34: =B7 -> 3000 | D34: Ganancia del negocio | E34: =B38 -> 958.125
A35: Subtotal directo | B35: =B33+B34 -> 3650 | D35: Margen sobre venta | E35: =IFERROR(E34/B42,0) -> 0.191625
A36: Costos indirectos | B36: =B35*Config!B6 -> 182.5 | D36: Ingreso por hora trabajada | E36: =IFERROR(B42/B5,0) -> 2500
A37: Costo total real | B37: =B35+B36 -> 3832.5 | D37: Materiales % del precio | E37: =IFERROR(B33/B42,0) -> 0.13
A38: Ganancia objetivo | B38: =B37*Config!B5 -> 958.125 | D38: Mano de obra % del precio | E38: =IFERROR(B34/B42,0) -> 0.6
A39: Precio antes de comisión | B39: =B37+B38 -> 4790.625
A40: Comisión de pago/venta | B40: =IF(Config!B7=0,0,B39/(1-Config!B7)-B39) -> 0 | D40: Uso rápido
A41: Precio matemático | B41: =B39+B40 -> 4790.625 | D41: 1) Indica las horas reales de trabajo. 2) Para cada material pon precio de compra, cantidad total que trae y cantidad usada. 3) Para un zíper, broche o llavín individual usa 1 comprado y 1 usado. 4) Ajusta mano de obra, ganancia, indirectos, comisión y redondeo en Configuración. 5) El PRECIO SUGERIDO se calcula automáticamente y sirve para cualquier producto.
A42: PRECIO SUGERIDO | B42: =ROUNDUP(B41/Config!B8,0)*Config!B8 -> 5000

Sheet Anyelo
A1: Calculadora universal de precios para crochet
A3: Datos del producto
A4: Nombre / referencia | B4: mapache
A5: Tiempo total (horas) | B5: 1.5
A6: Mano de obra por hora | B6: =Config!B4 -> 1500
A7: Costo mano de obra | B7: =B5*B6 -> 2250
A9: Materiales y accesorios
A10: Material / accesorio | B10: Precio compra | C10: Cantidad comprada | D10: Cantidad usada | E10: Unidad | F10: Costo usado | G10: Notas | H10: Tipo
A11: Lana / hilo principal | B11: 2600 | C11: 100 | D11: 17 | E11: g | F11: =IFERROR((B11/C11)*D11,0) -> 442 | G11: Ej.: ovillo de 100 g | H11: Material
A12: Lana / hilo secundario | B12: 0 | C12: 0 | D12: 0 | E12: g | F12: =IFERROR((B12/C12)*D12,0) -> 0 | H12: Material
A13: Zíper | B13: 0 | C13: 1 | D13: 0 | E13: unidad | F13: =IFERROR((B13/C13)*D13,0) -> 0 | H13: Accesorio
A14: Llavín / herraje | B14: 50 | C14: 1 | D14: 0 | E14: unidad | F14: =IFERROR((B14/C14)*D14,0) -> 0 | H14: Accesorio
A15: broches | B15: 625 | C15: 30 | D15: 0 | E15: unidad | F15: =IFERROR((B15/C15)*D15,0) -> 0 | H15: Material
A16: ojitos | B16: 250 | C16: 5 | D16: 0 | F16: =IFERROR((B16/C16)*D16,0) -> 0 | H16: Material
A17: relleno | B17: 5400 | C17: 1000 | D17: 6 | E17: g | F17: =IFERROR((B17/C17)*D17,0) -> 32.4 | H17: Material
B18: 0 | C18: 1 | D18: 0 | F18: =IFERROR((B18/C18)*D18,0) -> 0 | H18: Material
B19: 0 | C19: 1 | D19: 0 | F19: =IFERROR((B19/C19)*D19,0) -> 0 | H19: Material
B20: 0 | C20: 1 | D20: 0 | F20: =IFERROR((B20/C20)*D20,0) -> 0 | H20: Material
B21: 0 | C21: 1 | D21: 0 | F21: =IFERROR((B21/C21)*D21,0) -> 0 | H21: Material
B22: 0 | C22: 1 | D22: 0 | F22: =IFERROR((B22/C22)*D22,0) -> 0 | H22: Material
B23: 0 | C23: 1 | D23: 0 | F23: =IFERROR((B23/C23)*D23,0) -> 0 | H23: Material
B24: 0 | C24: 1 | D24: 0 | F24: =IFERROR((B24/C24)*D24,0) -> 0 | H24: Material
B25: 0 | C25: 1 | D25: 0 | F25: =IFERROR((B25/C25)*D25,0) -> 0 | H25: Material
B26: 0 | C26: 1 | D26: 0 | F26: =IFERROR((B26/C26)*D26,0) -> 0 | H26: Material
B27: 0 | C27: 1 | D27: 0 | F27: =IFERROR((B27/C27)*D27,0) -> 0 | H27: Material
B28: 0 | C28: 1 | D28: 0 | F28: =IFERROR((B28/C28)*D28,0) -> 0 | H28: Material
B29: 0 | C29: 1 | D29: 0 | F29: =IFERROR((B29/C29)*D29,0) -> 0 | H29: Material
B30: 0 | C30: 1 | D30: 0 | F30: =IFERROR((B30/C30)*D30,0) -> 0 | H30: Material
A32: Resumen de precio
A33: Costo materiales/accesorios | B33: =SUM(F11:F30) -> 474.4 | D33: Indicadores
A34: Costo mano de obra | B34: =B7 -> 2250 | D34: Ganancia del negocio | E34: =B38 -> 715.155
A35: Subtotal directo | B35: =B33+B34 -> 2724.4 | D35: Margen sobre venta | E35: =IFERROR(E34/B42,0) -> 0.17878875
A36: Costos indirectos | B36: =B35*Config!B6 -> 136.22 | D36: Ingreso por hora trabajada | E36: =IFERROR(B42/B5,0) -> 2666.6667
A37: Costo total real | B37: =B35+B36 -> 2860.62 | D37: Materiales % del precio | E37: =IFERROR(B33/B42,0) -> 0.1186
A38: Ganancia objetivo | B38: =B37*Config!B5 -> 715.155 | D38: Mano de obra % del precio | E38: =IFERROR(B34/B42,0) -> 0.5625
A39: Precio antes de comisión | B39: =B37+B38 -> 3575.775
A40: Comisión de pago/venta | B40: =IF(Config!B7=0,0,B39/(1-Config!B7)-B39) -> 0 | D40: Uso rápido
A41: Precio matemático | B41: =B39+B40 -> 3575.775 | D41: 1) Indica las horas reales de trabajo. 2) Para cada material pon precio de compra, cantidad total que trae y cantidad usada. 3) Para un zíper, broche o llavín individual usa 1 comprado y 1 usado. 4) Ajusta mano de obra, ganancia, indirectos, comisión y redondeo en Configuración. 5) El PRECIO SUGERIDO se calcula automáticamente y sirve para cualquier producto.
A42: PRECIO SUGERIDO | B42: =ROUNDUP(B41/Config!B8,0)*Config!B8 -> 4000

Sheet Muñe ale
A1: Calculadora universal de precios para crochet
A3: Datos del producto
A4: Nombre / referencia | B4: Muñequitos
A5: Tiempo total (horas) | B5: 1.5
A6: Mano de obra por hora | B6: =Config!B4 -> 1500
A7: Costo mano de obra | B7: =B5*B6 -> 2250
A9: Materiales y accesorios
A10: Material / accesorio | B10: Precio compra | C10: Cantidad comprada | D10: Cantidad usada | E10: Unidad | F10: Costo usado | G10: Notas | H10: Tipo
A11: Lana / hilo principal | B11: 2600 | C11: 100 | D11: 25 | E11: g | F11: =IFERROR((B11/C11)*D11,0) -> 650 | G11: Ej.: ovillo de 100 g | H11: Material
A12: Lana / hilo secundario | B12: 0 | C12: 0 | D12: 0 | E12: g | F12: =IFERROR((B12/C12)*D12,0) -> 0 | H12: Material
A13: Zíper | B13: 0 | C13: 1 | D13: 0 | E13: unidad | F13: =IFERROR((B13/C13)*D13,0) -> 0 | H13: Accesorio
A14: Llavín / herraje | B14: 50 | C14: 1 | D14: 0 | E14: unidad | F14: =IFERROR((B14/C14)*D14,0) -> 0 | H14: Accesorio
A15: broches | B15: 625 | C15: 30 | D15: 0 | E15: unidad | F15: =IFERROR((B15/C15)*D15,0) -> 0 | H15: Material
A16: ojitos | B16: 250 | C16: 5 | D16: 1 | F16: =IFERROR((B16/C16)*D16,0) -> 50 | H16: Material
A17: relleno | B17: 5400 | C17: 1000 | D17: 7 | E17: g | F17: =IFERROR((B17/C17)*D17,0) -> 37.8 | H17: Material
B18: 0 | C18: 1 | D18: 0 | F18: =IFERROR((B18/C18)*D18,0) -> 0 | H18: Material
B19: 0 | C19: 1 | D19: 0 | F19: =IFERROR((B19/C19)*D19,0) -> 0 | H19: Material
B20: 0 | C20: 1 | D20: 0 | F20: =IFERROR((B20/C20)*D20,0) -> 0 | H20: Material
B21: 0 | C21: 1 | D21: 0 | F21: =IFERROR((B21/C21)*D21,0) -> 0 | H21: Material
B22: 0 | C22: 1 | D22: 0 | F22: =IFERROR((B22/C22)*D22,0) -> 0 | H22: Material
B23: 0 | C23: 1 | D23: 0 | F23: =IFERROR((B23/C23)*D23,0) -> 0 | H23: Material
B24: 0 | C24: 1 | D24: 0 | F24: =IFERROR((B24/C24)*D24,0) -> 0 | H24: Material
B25: 0 | C25: 1 | D25: 0 | F25: =IFERROR((B25/C25)*D25,0) -> 0 | H25: Material
B26: 0 | C26: 1 | D26: 0 | F26: =IFERROR((B26/C26)*D26,0) -> 0 | H26: Material
B27: 0 | C27: 1 | D27: 0 | F27: =IFERROR((B27/C27)*D27,0) -> 0 | H27: Material
B28: 0 | C28: 1 | D28: 0 | F28: =IFERROR((B28/C28)*D28,0) -> 0 | H28: Material
B29: 0 | C29: 1 | D29: 0 | F29: =IFERROR((B29/C29)*D29,0) -> 0 | H29: Material
B30: 0 | C30: 1 | D30: 0 | F30: =IFERROR((B30/C30)*D30,0) -> 0 | H30: Material
A32: Resumen de precio
A33: Costo materiales/accesorios | B33: =SUM(F11:F30) -> 737.8 | D33: Indicadores
A34: Costo mano de obra | B34: =B7 -> 2250 | D34: Ganancia del negocio | E34: =B38 -> 784.2975
A35: Subtotal directo | B35: =B33+B34 -> 2987.8 | D35: Margen sobre venta | E35: =IFERROR(E34/B42,0) -> 0.19607437
A36: Costos indirectos | B36: =B35*Config!B6 -> 149.39 | D36: Ingreso por hora trabajada | E36: =IFERROR(B42/B5,0) -> 2666.6667
A37: Costo total real | B37: =B35+B36 -> 3137.19 | D37: Materiales % del precio | E37: =IFERROR(B33/B42,0) -> 0.18445
A38: Ganancia objetivo | B38: =B37*Config!B5 -> 784.2975 | D38: Mano de obra % del precio | E38: =IFERROR(B34/B42,0) -> 0.5625
A39: Precio antes de comisión | B39: =B37+B38 -> 3921.4875
A40: Comisión de pago/venta | B40: =IF(Config!B7=0,0,B39/(1-Config!B7)-B39) -> 0 | D40: Uso rápido
A41: Precio matemático | B41: =B39+B40 -> 3921.4875 | D41: 1) Indica las horas reales de trabajo. 2) Para cada material pon precio de compra, cantidad total que trae y cantidad usada. 3) Para un zíper, broche o llavín individual usa 1 comprado y 1 usado. 4) Ajusta mano de obra, ganancia, indirectos, comisión y redondeo en Configuración. 5) El PRECIO SUGERIDO se calcula automáticamente y sirve para cualquier producto.
A42: PRECIO SUGERIDO | B42: =ROUNDUP(B41/Config!B8,0)*Config!B8 -> 4000

Sheet Dahiky
A1: Calculadora universal de precios para crochet
A3: Datos del producto
A4: Nombre / referencia | B4: Gatito ale
A5: Tiempo total (horas) | B5: 1
A6: Mano de obra por hora | B6: =Config!B4 -> 1500
A7: Costo mano de obra | B7: =B5*B6 -> 1500
A9: Materiales y accesorios
A10: Material / accesorio | B10: Precio compra | C10: Cantidad comprada | D10: Cantidad usada | E10: Unidad | F10: Costo usado | G10: Notas | H10: Tipo
A11: Lana / hilo principal | B11: 2600 | C11: 100 | D11: 9 | E11: g | F11: =IFERROR((B11/C11)*D11,0) -> 234 | G11: Ej.: ovillo de 100 g | H11: Material
A12: Lana / hilo secundario | B12: 0 | C12: 0 | D12: 0 | E12: g | F12: =IFERROR((B12/C12)*D12,0) -> 0 | H12: Material
A13: Zíper | B13: 0 | C13: 1 | D13: 0 | E13: unidad | F13: =IFERROR((B13/C13)*D13,0) -> 0 | H13: Accesorio
A14: Llavín / herraje | B14: 50 | C14: 1 | D14: 1 | E14: unidad | F14: =IFERROR((B14/C14)*D14,0) -> 50 | H14: Accesorio
A15: broches | B15: 625 | C15: 30 | D15: 0 | E15: unidad | F15: =IFERROR((B15/C15)*D15,0) -> 0 | H15: Material
A16: ojitos | B16: 250 | C16: 5 | D16: 1 | F16: =IFERROR((B16/C16)*D16,0) -> 50 | H16: Material
A17: relleno | B17: 5400 | C17: 1000 | D17: 4 | E17: g | F17: =IFERROR((B17/C17)*D17,0) -> 21.6 | H17: Material
B18: 0 | C18: 1 | D18: 0 | F18: =IFERROR((B18/C18)*D18,0) -> 0 | H18: Material
B19: 0 | C19: 1 | D19: 0 | F19: =IFERROR((B19/C19)*D19,0) -> 0 | H19: Material
B20: 0 | C20: 1 | D20: 0 | F20: =IFERROR((B20/C20)*D20,0) -> 0 | H20: Material
B21: 0 | C21: 1 | D21: 0 | F21: =IFERROR((B21/C21)*D21,0) -> 0 | H21: Material
B22: 0 | C22: 1 | D22: 0 | F22: =IFERROR((B22/C22)*D22,0) -> 0 | H22: Material
B23: 0 | C23: 1 | D23: 0 | F23: =IFERROR((B23/C23)*D23,0) -> 0 | H23: Material
B24: 0 | C24: 1 | D24: 0 | F24: =IFERROR((B24/C24)*D24,0) -> 0 | H24: Material
B25: 0 | C25: 1 | D25: 0 | F25: =IFERROR((B25/C25)*D25,0) -> 0 | H25: Material
B26: 0 | C26: 1 | D26: 0 | F26: =IFERROR((B26/C26)*D26,0) -> 0 | H26: Material
B27: 0 | C27: 1 | D27: 0 | F27: =IFERROR((B27/C27)*D27,0) -> 0 | H27: Material
B28: 0 | C28: 1 | D28: 0 | F28: =IFERROR((B28/C28)*D28,0) -> 0 | H28: Material
B29: 0 | C29: 1 | D29: 0 | F29: =IFERROR((B29/C29)*D29,0) -> 0 | H29: Material
B30: 0 | C30: 1 | D30: 0 | F30: =IFERROR((B30/C30)*D30,0) -> 0 | H30: Material
A32: Resumen de precio
A33: Costo materiales/accesorios | B33: =SUM(F11:F30) -> 355.6 | D33: Indicadores
A34: Costo mano de obra | B34: =B7 -> 1500 | D34: Ganancia del negocio | E34: =B38 -> 487.095
A35: Subtotal directo | B35: =B33+B34 -> 1855.6 | D35: Margen sobre venta | E35: =IFERROR(E34/B42,0) -> 0.194838
A36: Costos indirectos | B36: =B35*Config!B6 -> 92.78 | D36: Ingreso por hora trabajada | E36: =IFERROR(B42/B5,0) -> 2500
A37: Costo total real | B37: =B35+B36 -> 1948.38 | D37: Materiales % del precio | E37: =IFERROR(B33/B42,0) -> 0.14224
A38: Ganancia objetivo | B38: =B37*Config!B5 -> 487.095 | D38: Mano de obra % del precio | E38: =IFERROR(B34/B42,0) -> 0.6
A39: Precio antes de comisión | B39: =B37+B38 -> 2435.475
A40: Comisión de pago/venta | B40: =IF(Config!B7=0,0,B39/(1-Config!B7)-B39) -> 0 | D40: Uso rápido
A41: Precio matemático | B41: =B39+B40 -> 2435.475 | D41: 1) Indica las horas reales de trabajo. 2) Para cada material pon precio de compra, cantidad total que trae y cantidad usada. 3) Para un zíper, broche o llavín individual usa 1 comprado y 1 usado. 4) Ajusta mano de obra, ganancia, indirectos, comisión y redondeo en Configuración. 5) El PRECIO SUGERIDO se calcula automáticamente y sirve para cualquier producto.
A42: PRECIO SUGERIDO | B42: =ROUNDUP(B41/Config!B8,0)*Config!B8 -> 2500

Sheet Taza
A1: Calculadora universal de precios para crochet
A3: Datos del producto
A4: Nombre / referencia | B4: Conejo
A5: Tiempo total (horas) | B5: 3.5
A6: Mano de obra por hora | B6: =Config!B4 -> 1500
A7: Costo mano de obra | B7: =B5*B6 -> 5250
A9: Materiales y accesorios
A10: Material / accesorio | B10: Precio compra | C10: Cantidad comprada | D10: Cantidad usada | E10: Unidad | F10: Costo usado | G10: Notas | H10: Tipo
A11: Lana / hilo principal | B11: 2600 | C11: 100 | D11: 25 | E11: g | F11: =IFERROR((B11/C11)*D11,0) -> 650 | G11: Ej.: ovillo de 100 g | H11: Material
A12: Lana / hilo secundario | B12: 0 | C12: 0 | D12: 0 | E12: g | F12: =IFERROR((B12/C12)*D12,0) -> 0 | H12: Material
A13: Zíper | B13: 0 | C13: 1 | D13: 0 | E13: unidad | F13: =IFERROR((B13/C13)*D13,0) -> 0 | H13: Accesorio
A14: Llavín / herraje | B14: 0 | C14: 1 | D14: 0 | E14: unidad | F14: =IFERROR((B14/C14)*D14,0) -> 0 | H14: Accesorio
A15: broches | B15: 625 | C15: 30 | D15: 2 | E15: unidad | F15: =IFERROR((B15/C15)*D15,0) -> 41.666667 | H15: Material
A16: ojitos | B16: 250 | C16: 5 | D16: 1 | F16: =IFERROR((B16/C16)*D16,0) -> 50 | H16: Material
B17: 0 | C17: 1 | D17: 0 | F17: =IFERROR((B17/C17)*D17,0) -> 0 | H17: Material
B18: 0 | C18: 1 | D18: 0 | F18: =IFERROR((B18/C18)*D18,0) -> 0 | H18: Material
B19: 0 | C19: 1 | D19: 0 | F19: =IFERROR((B19/C19)*D19,0) -> 0 | H19: Material
B20: 0 | C20: 1 | D20: 0 | F20: =IFERROR((B20/C20)*D20,0) -> 0 | H20: Material
B21: 0 | C21: 1 | D21: 0 | F21: =IFERROR((B21/C21)*D21,0) -> 0 | H21: Material
B22: 0 | C22: 1 | D22: 0 | F22: =IFERROR((B22/C22)*D22,0) -> 0 | H22: Material
B23: 0 | C23: 1 | D23: 0 | F23: =IFERROR((B23/C23)*D23,0) -> 0 | H23: Material
B24: 0 | C24: 1 | D24: 0 | F24: =IFERROR((B24/C24)*D24,0) -> 0 | H24: Material
B25: 0 | C25: 1 | D25: 0 | F25: =IFERROR((B25/C25)*D25,0) -> 0 | H25: Material
B26: 0 | C26: 1 | D26: 0 | F26: =IFERROR((B26/C26)*D26,0) -> 0 | H26: Material
B27: 0 | C27: 1 | D27: 0 | F27: =IFERROR((B27/C27)*D27,0) -> 0 | H27: Material
B28: 0 | C28: 1 | D28: 0 | F28: =IFERROR((B28/C28)*D28,0) -> 0 | H28: Material
... B30: 0 | C30: 1 | D30: 0 | F30: =IFERROR((B30/C30)*D30,0) -> 0 | H30: Material
A32: Resumen de precio
A33: Costo materiales/accesorios | B33: =SUM(F11:F30) -> 741.66667 | D33: Indicadores
A34: Costo mano de obra | B34: =B7 -> 5250 | D34: Ganancia del negocio | E34: =B38 -> 1572.8125
A35: Subtotal directo | B35: =B33+B34 -> 5991.6667 | D35: Margen sobre venta | E35: =IFERROR(E34/B42,0) -> 0.19660156
A36: Costos indirectos | B36: =B35*Config!B6 -> 299.58333 | D36: Ingreso por hora trabajada | E36: =IFERROR(B42/B5,0) -> 2285.7143
A37: Costo total real | B37: =B35+B36 -> 6291.25 | D37: Materiales % del precio | E37: =IFERROR(B33/B42,0) -> 0.092708333
A38: Ganancia objetivo | B38: =B37*Config!B5 -> 1572.8125 | D38: Mano de obra % del precio | E38: =IFERROR(B34/B42,0) -> 0.65625
A39: Precio antes de comisión | B39: =B37+B38 -> 7864.0625
A40: Comisión de pago/venta | B40: =IF(Config!B7=0,0,B39/(1-Config!B7)-B39) -> 0 | D40: Uso rápido
A41: Precio matemático | B41: =B39+B40 -> 7864.0625 | D41: 1) Indica las horas reales de trabajo. 2) Para cada material pon precio de compra, cantidad total que trae y cantidad usada. 3) Para un zíper, broche o llavín individual usa 1 comprado y 1 usado. 4) Ajusta mano de obra, ganancia, indirectos, comisión y redondeo en Configuración. 5) El PRECIO SUGERIDO se calcula automáticamente y sirve para cualquier producto.
A42: PRECIO SUGERIDO | B42: =ROUNDUP(B41/Config!B8,0)*Config!B8 -> 8000

Sheet Conejo
A1: Calculadora universal de precios para crochet
A3: Datos del producto
A4: Nombre / referencia | B4: Conejo
A5: Tiempo total (horas) | B5: 3.5
A6: Mano de obra por hora | B6: =Config!B4 -> 1500
A7: Costo mano de obra | B7: =B5*B6 -> 5250
A9: Materiales y accesorios
A10: Material / accesorio | B10: Precio compra | C10: Cantidad comprada | D10: Cantidad usada | E10: Unidad | F10: Costo usado | G10: Notas | H10: Tipo
A11: Lana / hilo principal | B11: 2600 | C11: 100 | D11: 25 | E11: g | F11: =IFERROR((B11/C11)*D11,0) -> 650 | G11: Ej.: ovillo de 100 g | H11: Material
A12: Lana / hilo secundario | B12: 0 | C12: 0 | D12: 0 | E12: g | F12: =IFERROR((B12/C12)*D12,0) -> 0 | H12: Material
A13: Zíper | B13: 0 | C13: 1 | D13: 0 | E13: unidad | F13: =IFERROR((B13/C13)*D13,0) -> 0 | H13: Accesorio
A14: Llavín / herraje | B14: 0 | C14: 1 | D14: 0 | E14: unidad | F14: =IFERROR((B14/C14)*D14,0) -> 0 | H14: Accesorio
A15: broches | B15: 625 | C15: 30 | D15: 2 | E15: unidad | F15: =IFERROR((B15/C15)*D15,0) -> 41.666667 | H15: Material
A16: ojitos | B16: 250 | C16: 5 | D16: 1 | F16: =IFERROR((B16/C16)*D16,0) -> 50 | H16: Material
B17: 0 | C17: 1 | D17: 0 | F17: =IFERROR((B17/C17)*D17,0) -> 0 | H17: Material
B18: 0 | C18: 1 | D18: 0 | F18: =IFERROR((B18/C18)*D18,0) -> 0 | H18: Material
B19: 0 | C19: 1 | D19: 0 | F19: =IFERROR((B19/C19)*D19,0) -> 0 | H19: Material
B20: 0 | C20: 1 | D20: 0 | F20: =IFERROR((B20/C20)*D20,0) -> 0 | H20: Material
B21: 0 | C21: 1 | D21: 0 | F21: =IFERROR((B21/C21)*D21,0) -> 0 | H21: Material
B22: 0 | C22: 1 | D22: 0 | F22: =IFERROR((B22/C22)*D22,0) -> 0 | H22: Material
B23: 0 | C23: 1 | D23: 0 | F23: =IFERROR((B23/C23)*D23,0) -> 0 | H23: Material
B24: 0 | C24: 1 | D24: 0 | F24: =IFERROR((B24/C24)*D24,0) -> 0 | H24: Material
B25: 0 | C25: 1 | D25: 0 | F25: =IFERROR((B25/C25)*D25,0) -> 0 | H25: Material
B26: 0 | C26: 1 | D26: 0 | F26: =IFERROR((B26/C26)*D26,0) -> 0 | H26: Material
B27: 0 | C27: 1 | D27: 0 | F27: =IFERROR((B27/C27)*D27,0) -> 0 | H27: Material
B28: 0 | C28: 1 | D28: 0 | F28: =IFERROR((B28/C28)*D28,0) -> 0 | H28: Material
... B30: 0 | C30: 1 | D30: 0 | F30: =IFERROR((B30/C30)*D30,0) -> 0 | H30: Material
A32: Resumen de precio
A33: Costo materiales/accesorios | B33: =SUM(F11:F30) -> 741.66667 | D33: Indicadores
A34: Costo mano de obra | B34: =B7 -> 5250 | D34: Ganancia del negocio | E34: =B38 -> 1572.8125
A35: Subtotal directo | B35: =B33+B34 -> 5991.6667 | D35: Margen sobre venta | E35: =IFERROR(E34/B42,0) -> 0.19660156
A36: Costos indirectos | B36: =B35*Config!B6 -> 299.58333 | D36: Ingreso por hora trabajada | E36: =IFERROR(B42/B5,0) -> 2285.7143
A37: Costo total real | B37: =B35+B36 -> 6291.25 | D37: Materiales % del precio | E37: =IFERROR(B33/B42,0) -> 0.092708333
A38: Ganancia objetivo | B38: =B37*Config!B5 -> 1572.8125 | D38: Mano de obra % del precio | E38: =IFERROR(B34/B42,0) -> 0.65625
A39: Precio antes de comisión | B39: =B37+B38 -> 7864.0625
A40: Comisión de pago/venta | B40: =IF(Config!B7=0,0,B39/(1-Config!B7)-B39) -> 0 | D40: Uso rápido
A41: Precio matemático | B41: =B39+B40 -> 7864.0625 | D41: 1) Indica las horas reales de trabajo. 2) Para cada material pon precio de compra, cantidad total que trae y cantidad usada. 3) Para un zíper, broche o llavín individual usa 1 comprado y 1 usado. 4) Ajusta mano de obra, ganancia, indirectos, comisión y redondeo en Configuración. 5) El PRECIO SUGERIDO se calcula automáticamente y sirve para cualquier producto.
A42: PRECIO SUGERIDO | B42: =ROUNDUP(B41/Config!B8,0)*Config!B8 -> 8000

Sheet Gallina
A1: Calculadora universal de precios para crochet
A3: Datos del producto
A4: Nombre / referencia | B4: Gallina separador
A5: Tiempo total (horas) | B5: 1
A6: Mano de obra por hora | B6: =Config!B4 -> 1500
A7: Costo mano de obra | B7: =B5*B6 -> 1500
A9: Materiales y accesorios
A10: Material / accesorio | B10: Precio compra | C10: Cantidad comprada | D10: Cantidad usada | E10: Unidad | F10: Costo usado | G10: Notas | H10: Tipo
A11: Lana / hilo principal | B11: 2600 | C11: 100 | D11: 12 | E11: g | F11: =IFERROR((B11/C11)*D11,0) -> 312 | G11: Ej.: ovillo de 100 g | H11: Material
A12: Lana / hilo secundario | B12: 0 | C12: 0 | D12: 0 | E12: g | F12: =IFERROR((B12/C12)*D12,0) -> 0 | H12: Material
A13: Zíper | B13: 0 | C13: 1 | D13: 0 | E13: unidad | F13: =IFERROR((B13/C13)*D13,0) -> 0 | H13: Accesorio
A14: Llavín / herraje | B14: 0 | C14: 1 | D14: 0 | E14: unidad | F14: =IFERROR((B14/C14)*D14,0) -> 0 | H14: Accesorio
A15: broches | B15: 625 | C15: 30 | D15: 0 | E15: unidad | F15: =IFERROR((B15/C15)*D15,0) -> 0 | H15: Material
A16: ojitos | B16: 250 | C16: 5 | D16: 1 | F16: =IFERROR((B16/C16)*D16,0) -> 50 | H16: Material
B17: 0 | C17: 1 | D17: 0 | F17: =IFERROR((B17/C17)*D17,0) -> 0 | H17: Material
B18: 0 | C18: 1 | D18: 0 | F18: =IFERROR((B18/C18)*D18,0) -> 0 | H18: Material
B19: 0 | C19: 1 | D19: 0 | F19: =IFERROR((B19/C19)*D19,0) -> 0 | H19: Material
B20: 0 | C20: 1 | D20: 0 | F20: =IFERROR((B20/C20)*D20,0) -> 0 | H20: Material
B21: 0 | C21: 1 | D21: 0 | F21: =IFERROR((B21/C21)*D21,0) -> 0 | H21: Material
B22: 0 | C22: 1 | D22: 0 | F22: =IFERROR((B22/C22)*D22,0) -> 0 | H22: Material
B23: 0 | C23: 1 | D23: 0 | F23: =IFERROR((B23/C23)*D23,0) -> 0 | H23: Material
B24: 0 | C24: 1 | D24: 0 | F24: =IFERROR((B24/C24)*D24,0) -> 0 | H24: Material
B25: 0 | C25: 1 | D25: 0 | F25: =IFERROR((B25/C25)*D25,0) -> 0 | H25: Material
B26: 0 | C26: 1 | D26: 0 | F26: =IFERROR((B26/C26)*D26,0) -> 0 | H26: Material
B27: 0 | C27: 1 | D27: 0 | F27: =IFERROR((B27/C27)*D27,0) -> 0 | H27: Material
B28: 0 | C28: 1 | D28: 0 | F28: =IFERROR((B28/C28)*D28,0) -> 0 | H28: Material
... B30: 0 | C30: 1 | D30: 0 | F30: =IFERROR((B30/C30)*D30,0) -> 0 | H30: Material
A32: Resumen de precio
A33: Costo materiales/accesorios | B33: =SUM(F11:F30) -> 362 | D33: Indicadores
A34: Costo mano de obra | B34: =B7 -> 1500 | D34: Ganancia del negocio | E34: =B38 -> 488.775
A35: Subtotal directo | B35: =B33+B34 -> 1862 | D35: Margen sobre venta | E35: =IFERROR(E34/B42,0) -> 0.19551
A36: Costos indirectos | B36: =B35*Config!B6 -> 93.1 | D36: Ingreso por hora trabajada | E36: =IFERROR(B42/B5,0) -> 2500
A37: Costo total real | B37: =B35+B36 -> 1955.1 | D37: Materiales % del precio | E37: =IFERROR(B33/B42,0) -> 0.1448
A38: Ganancia objetivo | B38: =B37*Config!B5 -> 488.775 | D38: Mano de obra % del precio | E38: =IFERROR(B34/B42,0) -> 0.6
A39: Precio antes de comisión | B39: =B37+B38 -> 2443.875
A40: Comisión de pago/venta | B40: =IF(Config!B7=0,0,B39/(1-Config!B7)-B39) -> 0 | D40: Uso rápido
A41: Precio matemático | B41: =B39+B40 -> 2443.875 | D41: 1) Indica las horas reales de trabajo. 2) Para cada material pon precio de compra, cantidad total que trae y cantidad usada. 3) Para un zíper, broche o llavín individual usa 1 comprado y 1 usado. 4) Ajusta mano de obra, ganancia, indirectos, comisión y redondeo en Configuración. 5) El PRECIO SUGERIDO se calcula automáticamente y sirve para cualquier producto.
A42: PRECIO SUGERIDO | B42: =ROUNDUP(B41/Config!B8,0)*Config!B8 -> 2500

Sheet Lazo
A1: Calculadora universal de precios para crochet
A3: Datos del producto
A4: Nombre / referencia | B4: separador lazo
A5: Tiempo total (horas) | B5: 1
A6: Mano de obra por hora | B6: =Config!B4 -> 1500
A7: Costo mano de obra | B7: =B5*B6 -> 1500
A9: Materiales y accesorios
A10: Material / accesorio | B10: Precio compra | C10: Cantidad comprada | D10: Cantidad usada | E10: Unidad | F10: Costo usado | G10: Notas | H10: Tipo
A11: Lana / hilo principal | B11: 2600 | C11: 100 | D11: 6 | E11: g | F11: =IFERROR((B11/C11)*D11,0) -> 156 | G11: Ej.: ovillo de 100 g | H11: Material
A12: Lana / hilo secundario | B12: 0 | C12: 0 | D12: 0 | E12: g | F12: =IFERROR((B12/C12)*D12,0) -> 0 | H12: Material
A13: Zíper | B13: 0 | C13: 1 | D13: 0 | E13: unidad | F13: =IFERROR((B13/C13)*D13,0) -> 0 | H13: Accesorio
A14: Llavín / herraje | B14: 0 | C14: 1 | D14: 0 | E14: unidad | F14: =IFERROR((B14/C14)*D14,0) -> 0 | H14: Accesorio
A15: broches | B15: 0 | C15: 0 | D15: 0 | E15: unidad | F15: =IFERROR((B15/C15)*D15,0) -> 0 | H15: Material
B16: 0 | C16: 1 | D16: 0 | F16: =IFERROR((B16/C16)*D16,0) -> 0 | H16: Material
B17: 0 | C17: 1 | D17: 0 | F17: =IFERROR((B17/C17)*D17,0) -> 0 | H17: Material
B18: 0 | C18: 1 | D18: 0 | F18: =IFERROR((B18/C18)*D18,0) -> 0 | H18: Material
B19: 0 | C19: 1 | D19: 0 | F19: =IFERROR((B19/C19)*D19,0) -> 0 | H19: Material
B20: 0 | C20: 1 | D20: 0 | F20: =IFERROR((B20/C20)*D20,0) -> 0 | H20: Material
B21: 0 | C21: 1 | D21: 0 | F21: =IFERROR((B21/C21)*D21,0) -> 0 | H21: Material
B22: 0 | C22: 1 | D22: 0 | F22: =IFERROR((B22/C22)*D22,0) -> 0 | H22: Material
B23: 0 | C23: 1 | D23: 0 | F23: =IFERROR((B23/C23)*D23,0) -> 0 | H23: Material
B24: 0 | C24: 1 | D24: 0 | F24: =IFERROR((B24/C24)*D24,0) -> 0 | H24: Material
B25: 0 | C25: 1 | D25: 0 | F25: =IFERROR((B25/C25)*D25,0) -> 0 | H25: Material
B26: 0 | C26: 1 | D26: 0 | F26: =IFERROR((B26/C26)*D26,0) -> 0 | H26: Material
B27: 0 | C27: 1 | D27: 0 | F27: =IFERROR((B27/C27)*D27,0) -> 0 | H27: Material
... B30: 0 | C30: 1 | D30: 0 | F30: =IFERROR((B30/C30)*D30,0) -> 0 | H30: Material
A32: Resumen de precio
A33: Costo materiales/accesorios | B33: =SUM(F11:F30) -> 156 | D33: Indicadores
A34: Costo mano de obra | B34: =B7 -> 1500 | D34: Ganancia del negocio | E34: =B38 -> 434.7
A35: Subtotal directo | B35: =B33+B34 -> 1656 | D35: Margen sobre venta | E35: =IFERROR(E34/B42,0) -> 0.17388
A36: Costos indirectos | B36: =B35*Config!B6 -> 82.8 | D36: Ingreso por hora trabajada | E36: =IFERROR(B42/B5,0) -> 2500
A37: Costo total real | B37: =B35+B36 -> 1738.8 | D37: Materiales % del precio | E37: =IFERROR(B33/B42,0) -> 0.0624
A38: Ganancia objetivo | B38: =B37*Config!B5 -> 434.7 | D38: Mano de obra % del precio | E38: =IFERROR(B34/B42,0) -> 0.6
A39: Precio antes de comisión | B39: =B37+B38 -> 2173.5
A40: Comisión de pago/venta | B40: =IF(Config!B7=0,0,B39/(1-Config!B7)-B39) -> 0 | D40: Uso rápido
A41: Precio matemático | B41: =B39+B40 -> 2173.5 | D41: 1) Indica las horas reales de trabajo. 2) Para cada material pon precio de compra, cantidad total que trae y cantidad usada. 3) Para un zíper, broche o llavín individual usa 1 comprado y 1 usado. 4) Ajusta mano de obra, ganancia, indirectos, comisión y redondeo en Configuración. 5) El PRECIO SUGERIDO se calcula automáticamente y sirve para cualquier producto.
A42: PRECIO SUGERIDO | B42: =ROUNDUP(B41/Config!B8,0)*Config!B8 -> 2500

Sheet Gancito
A1: Calculadora universal de precios para crochet
A3: Datos del producto
A4: Nombre / referencia | B4: Gancito
A5: Tiempo total (horas) | B5: 2
A6: Mano de obra por hora | B6: =Config!B4 -> 1500
A7: Costo mano de obra | B7: =B5*B6 -> 3000
A9: Materiales y accesorios
A10: Material / accesorio | B10: Precio compra | C10: Cantidad comprada | D10: Cantidad usada | E10: Unidad | F10: Costo usado | G10: Notas | H10: Tipo
A11: Lana / hilo principal | B11: 2600 | C11: 100 | D11: 16 | E11: g | F11: =IFERROR((B11/C11)*D11,0) -> 416 | G11: Ej.: ovillo de 100 g | H11: Material
A12: Lana / hilo secundario | B12: 0 | C12: 0 | D12: 0 | E12: g | F12: =IFERROR((B12/C12)*D12,0) -> 0 | H12: Material
A13: Zíper | B13: 0 | C13: 1 | D13: 0 | E13: unidad | F13: =IFERROR((B13/C13)*D13,0) -> 0 | H13: Accesorio
A14: Llavín / herraje | B14: 0 | C14: 1 | D14: 0 | E14: unidad | F14: =IFERROR((B14/C14)*D14,0) -> 0 | H14: Accesorio
A15: broches | B15: 625 | C15: 30 | D15: 2 | E15: unidad | F15: =IFERROR((B15/C15)*D15,0) -> 41.666667 | H15: Material
A16: ojitos | B16: 250 | C16: 5 | D16: 1 | F16: =IFERROR((B16/C16)*D16,0) -> 50 | H16: Material
B17: 0 | C17: 1 | D17: 0 | F17: =IFERROR((B17/C17)*D17,0) -> 0 | H17: Material
B18: 0 | C18: 1 | D18: 0 | F18: =IFERROR((B18/C18)*D18,0) -> 0 | H18: Material
B19: 0 | C19: 1 | D19: 0 | F19: =IFERROR((B19/C19)*D19,0) -> 0 | H19: Material
B20: 0 | C20: 1 | D20: 0 | F20: =IFERROR((B20/C20)*D20,0) -> 0 | H20: Material
B21: 0 | C21: 1 | D21: 0 | F21: =IFERROR((B21/C21)*D21,0) -> 0 | H21: Material
B22: 0 | C22: 1 | D22: 0 | F22: =IFERROR((B22/C22)*D22,0) -> 0 | H22: Material
B23: 0 | C23: 1 | D23: 0 | F23: =IFERROR((B23/C23)*D23,0) -> 0 | H23: Material
B24: 0 | C24: 1 | D24: 0 | F24: =IFERROR((B24/C24)*D24,0) -> 0 | H24: Material
B25: 0 | C25: 1 | D25: 0 | F25: =IFERROR((B25/C25)*D25,0) -> 0 | H25: Material
B26: 0 | C26: 1 | D26: 0 | F26: =IFERROR((B26/C26)*D26,0) -> 0 | H26: Material
B27: 0 | C27: 1 | D27: 0 | F27: =IFERROR((B27/C27)*D27,0) -> 0 | H27: Material
B28: 0 | C28: 1 | D28: 0 | F28: =IFERROR((B28/C28)*D28,0) -> 0 | H28: Material
... B30: 0 | C30: 1 | D30: 0 | F30: =IFERROR((B30/C30)*D30,0) -> 0 | H30: Material
A32: Resumen de precio
A33: Costo materiales/accesorios | B33: =SUM(F11:F30) -> 507.66667 | D33: Indicadores
A34: Costo mano de obra | B34: =B7 -> 3000 | D34: Ganancia del negocio | E34: =B38 -> 920.7625
A35: Subtotal directo | B35: =B33+B34 -> 3507.6667 | D35: Margen sobre venta | E35: =IFERROR(E34/B42,0) -> 0.1841525
A36: Costos indirectos | B36: =B35*Config!B6 -> 175.38333 | D36: Ingreso por hora trabajada | E36: =IFERROR(B42/B5,0) -> 2500
A37: Costo total real | B37: =B35+B36 -> 3683.05 | D37: Materiales % del precio | E37: =IFERROR(B33/B42,0) -> 0.10153333
A38: Ganancia objetivo | B38: =B37*Config!B5 -> 920.7625 | D38: Mano de obra % del precio | E38: =IFERROR(B34/B42,0) -> 0.6
A39: Precio antes de comisión | B39: =B37+B38 -> 4603.8125
A40: Comisión de pago/venta | B40: =IF(Config!B7=0,0,B39/(1-Config!B7)-B39) -> 0 | D40: Uso rápido
A41: Precio matemático | B41: =B39+B40 -> 4603.8125 | D41: 1) Indica las horas reales de trabajo. 2) Para cada material pon precio de compra, cantidad total que trae y cantidad usada. 3) Para un zíper, broche o llavín individual usa 1 comprado y 1 usado. 4) Ajusta mano de obra, ganancia, indirectos, comisión y redondeo en Configuración. 5) El PRECIO SUGERIDO se calcula automáticamente y sirve para cualquier producto.
A42: PRECIO SUGERIDO | B42: =ROUNDUP(B41/Config!B8,0)*Config!B8 -> 5000

Sheet Configuración
A1: Configuración general de precios
A3: Parámetro | B3: Valor | D3: Cómo usar
A4: Mano de obra por hora | B4: 1500 | D4: Monto que quieres pagarte por cada hora efectiva de trabajo.
A5: Ganancia objetivo | B5: 0.25 | D5: Ganancia adicional del negocio sobre el costo total.
A6: Costos indirectos | B6: 0.05 | D6: Empaque, electricidad, transporte menor, desgaste, etc.
A7: Comisión de pago/venta | B7: 0 | D7: Úsalo si una plataforma o método de pago cobra comisión.
A8: Redondeo comercial | B8: 500 | D8: El precio sugerido se redondea hacia arriba a este múltiplo.

Sheet Config
A1: Configuración general de precios
A3: Parámetro | B3: Valor | D3: Cómo usar
A4: Mano de obra por hora | B4: 1500 | D4: Monto que quieres pagarte por cada hora efectiva de trabajo.
A5: Ganancia objetivo | B5: 0.25 | D5: Ganancia adicional del negocio sobre el costo total.
A6: Costos indirectos | B6: 0.05 | D6: Empaque, electricidad, transporte menor, desgaste, etc.
A7: Comisión de pago/venta | B7: 0 | D7: Úsalo si una plataforma o método de pago cobra comisión.
A8: Redondeo comercial | B8: 500 | D8: El precio sugerido se redondea hacia arriba a este múltiplo.
